CHANGES.txt
LICENSE.txt
MANIFEST.in
README.txt
setup.py
js/__init__.py
js.signals.egg-info/PKG-INFO
js.signals.egg-info/SOURCES.txt
js.signals.egg-info/dependency_links.txt
js.signals.egg-info/entry_points.txt
js.signals.egg-info/namespace_packages.txt
js.signals.egg-info/not-zip-safe
js.signals.egg-info/requires.txt
js.signals.egg-info/top_level.txt
js/signals/__init__.py
js/signals/test_js-signals.txt
js/signals/resources/signals.js
js/signals/resources/signals.min.js