Metadata-Version: 1.0
Name: js.signals
Version: 0.8.1
Summary: Fanstatic packaging of js-signals
Home-page: UNKNOWN
Author: UNKNOWN
Author-email: UNKNOWN
License: MIT
Platform: UNKNOWN
